pyga/__init__.py
pyga/individual.py
pyga/constraints/__init__.py
pyga/constraints/base_constraints.py
pyga/constraints/constraint_manager.py
pyga/opt/__init__.py
pyga/opt/base_ga.py
pyga/opt/elite_soga.py
pyga/opt/soga.py
pyga/opt/ssga.py
pyga/utils/__init__.py
pyga/utils/crossovers.py
pyga/utils/history.py
pyga/utils/mutations.py
pyga/utils/recombinations.py
pyga/utils/selections.py
pyga/utils/termination_manager.py
pyga/utils/functions/__init__.py
pyga/utils/functions/single_objective.py
pyga/utils/plotting/__init__.py
pyga/utils/plotting/plot_designer.py
pyga/utils/plotting/plotting.py
tests/constraints/__init__.py
tests/constraints/test_constraint_manager.py
tests/opt/__init__.py
tests/opt/test_soga.py
tests/utils/__init__.py
tests/utils/test_crossovers.py
tests/utils/test_history.py
tests/utils/test_mutations.py
tests/utils/test_recombinations.py
tests/utils/test_selections.py
tests/utils/test_termination_manager.py
tests/utils/functions/__init__.py
tests/utils/functions/test_single_objective.py
PyGAopt-1.0.1.dist-info/LICENSE
PyGAopt-1.0.1.dist-info/METADATA
PyGAopt-1.0.1.dist-info/WHEEL
PyGAopt-1.0.1.dist-info/top_level.txt
PyGAopt-1.0.1.dist-info/RECORD
