Metadata-Version: 2.1
Name: PyGAopt
Version: 1.0.1
Summary: A Python Genetic Algorithm Library.
Home-page: https://github.com/danielkelshaw/PyGA
Author: Daniel Kelshaw
Author-email: daniel.j.kelshaw@gmail.com
License: MIT License
Platform: UNKNOWN
Requires-Dist: pytest (==5.4.1)
Requires-Dist: numpy (==1.18.2)
Requires-Dist: matplotlib (==3.2.1)
